{"items": [{"owner": {"reputation": 21136, "user_id": 2334192, "user_type": "registered", "profile_image": "https://i.stack.imgur.com/7u24l.jpg?s=128&g=1", "display_name": "James Holderness", "link": "https://stackoverflow.com/users/2334192/james-holderness"}, "creation_date": 1595548800, "down_vote_count": 0, "up_vote_count": 1, "post_id": 17798594, "question_id": 16405969, "timeline_type": "vote_aggregate"}, {"owner": {"reputation": 36633, "user_id": 533399, "user_type": "registered", "accept_rate": 95, "profile_image": "https://i.stack.imgur.com/Pem8D.jpg?s=128&g=1", "display_name": "DhruvPathak", "link": "https://stackoverflow.com/users/533399/dhruvpathak"}, "creation_date": 1592179200, "down_vote_count": 0, "up_vote_count": 1, "post_id": 16405969, "question_id": 16405969, "timeline_type": "vote_aggregate"}, {"owner": {"reputation": 36633, "user_id": 533399, "user_type": "registered", "accept_rate": 95, "profile_image": "https://i.stack.imgur.com/Pem8D.jpg?s=128&g=1", "display_name": "DhruvPathak", "link": "https://stackoverflow.com/users/533399/dhruvpathak"}, "creation_date": 1591228800, "down_vote_count": 0, "up_vote_count": 1, "post_id": 16405969, "question_id": 16405969, "timeline_type": "vote_aggregate"}, {"owner": {"reputation": 2081, "user_id": 1507867, "user_type": "registered", "profile_image": "https://www.gravatar.com/avatar/cb8a567bedc73c7d4a73353f8c006d82?s=128&d=identicon&r=PG", "display_name": "FastTurtle", "link": "https://stackoverflow.com/users/1507867/fastturtle"}, "creation_date": 1583107200, "down_vote_count": 0, "up_vote_count": 1, "post_id": 17684652, "question_id": 16405969, "timeline_type": "vote_aggregate"}, {"owner": {"reputation": 36633, "user_id": 533399, "user_type": "registered", "accept_rate": 95, "profile_image": "https://i.stack.imgur.com/Pem8D.jpg?s=128&g=1", "display_name": "DhruvPathak", "link": "https://stackoverflow.com/users/533399/dhruvpathak"}, "creation_date": 1565049600, "down_vote_count": 0, "up_vote_count": 1, "post_id": 16405969, "question_id": 16405969, "timeline_type": "vote_aggregate"}, {"owner": {"reputation": 36633, "user_id": 533399, "user_type": "registered", "accept_rate": 95, "profile_image": "https://i.stack.imgur.com/Pem8D.jpg?s=128&g=1", "display_name": "DhruvPathak", "link": "https://stackoverflow.com/users/533399/dhruvpathak"}, "creation_date": 1562198400, "down_vote_count": 0, "up_vote_count": 1, "post_id": 16405969, "question_id": 16405969, "timeline_type": "vote_aggregate"}, {"owner": {"reputation": 575, "user_id": 52667, "user_type": "registered", "profile_image": "https://www.gravatar.com/avatar/ca8e570c49e971d349aaad90412d4c27?s=128&d=identicon&r=PG", "display_name": "chees", "link": "https://stackoverflow.com/users/52667/chees"}, "creation_date": 1548979200, "down_vote_count": 0, "up_vote_count": 1, "post_id": 17789421, "question_id": 16405969, "timeline_type": "vote_aggregate"}, {"owner": {"reputation": 36633, "user_id": 533399, "user_type": "registered", "accept_rate": 95, "profile_image": "https://i.stack.imgur.com/Pem8D.jpg?s=128&g=1", "display_name": "DhruvPathak", "link": "https://stackoverflow.com/users/533399/dhruvpathak"}, "creation_date": 1538352000, "down_vote_count": 0, "up_vote_count": 1, "post_id": 16405969, "question_id": 16405969, "timeline_type": "vote_aggregate"}, {"owner": {"reputation": 1322, "user_id": 2574559, "user_type": "registered", "profile_image": "https://www.gravatar.com/avatar/0930eaece1635bab8e35a5fb9dfc1739?s=128&d=identicon&r=PG", "display_name": "bks", "link": "https://stackoverflow.com/users/2574559/bks"}, "creation_date": 1537747200, "down_vote_count": 1, "up_vote_count": 0, "post_id": 17779373, "question_id": 16405969, "timeline_type": "vote_aggregate"}, {"owner": {"reputation": 36633, "user_id": 533399, "user_type": "registered", "accept_rate": 95, "profile_image": "https://i.stack.imgur.com/Pem8D.jpg?s=128&g=1", "display_name": "DhruvPathak", "link": "https://stackoverflow.com/users/533399/dhruvpathak"}, "creation_date": 1534809600, "down_vote_count": 0, "up_vote_count": 1, "post_id": 16405969, "question_id": 16405969, "timeline_type": "vote_aggregate"}, {"owner": {"reputation": 36633, "user_id": 533399, "user_type": "registered", "accept_rate": 95, "profile_image": "https://i.stack.imgur.com/Pem8D.jpg?s=128&g=1", "display_name": "DhruvPathak", "link": "https://stackoverflow.com/users/533399/dhruvpathak"}, "creation_date": 1521158400, "down_vote_count": 0, "up_vote_count": 1, "post_id": 16405969, "question_id": 16405969, "timeline_type": "vote_aggregate"}, {"owner": {"reputation": 821, "user_id": 9203867, "user_type": "registered", "profile_image": "https://lh4.googleusercontent.com/-nT92Vp_nUaQ/AAAAAAAAAAI/AAAAAAAAAOc/L4Q30_FJ0pk/photo.jpg?sz=128", "display_name": "Wilhelm Liao", "link": "https://stackoverflow.com/users/9203867/wilhelm-liao"}, "creation_date": 1518246279, "post_id": 48718176, "question_id": 16405969, "timeline_type": "answer"}, {"owner": {"reputation": 36633, "user_id": 533399, "user_type": "registered", "accept_rate": 95, "profile_image": "https://i.stack.imgur.com/Pem8D.jpg?s=128&g=1", "display_name": "DhruvPathak", "link": "https://stackoverflow.com/users/533399/dhruvpathak"}, "creation_date": 1517406135, "comment_id": 84082268, "post_id": 16405969, "question_id": 16405969, "timeline_type": "comment"}, {"owner": {"reputation": 2714, "user_id": 7650686, "user_type": "registered", "profile_image": "https://www.gravatar.com/avatar/bbe418fb72dc9851771440b68381395f?s=128&d=identicon&r=PG&f=1", "display_name": "obgnaw", "link": "https://stackoverflow.com/users/7650686/obgnaw"}, "creation_date": 1517356800, "down_vote_count": 0, "up_vote_count": 2, "post_id": 48496708, "question_id": 16405969, "timeline_type": "vote_aggregate"}, {"user": {"reputation": 51, "user_id": 8971578, "user_type": "registered", "accept_rate": 100, "profile_image": "https://i.stack.imgur.com/fV0Tc.png?s=128&g=1", "display_name": "Harry", "link": "https://stackoverflow.com/users/8971578/harry"}, "creation_date": 1517327263, "post_id": 48496708, "question_id": 16405969, "timeline_type": "revision", "content_license": "CC BY-SA 3.0", "revision_guid": "44F8A9D6-8C9E-4F84-B83C-D2E5585B9DC2"}, {"owner": {"reputation": 36633, "user_id": 533399, "user_type": "registered", "accept_rate": 95, "profile_image": "https://i.stack.imgur.com/Pem8D.jpg?s=128&g=1", "display_name": "DhruvPathak", "link": "https://stackoverflow.com/users/533399/dhruvpathak"}, "creation_date": 1517270400, "down_vote_count": 0, "up_vote_count": 7, "post_id": 16405969, "question_id": 16405969, "timeline_type": "vote_aggregate"}, {"owner": {"reputation": 2081, "user_id": 1507867, "user_type": "registered", "profile_image": "https://www.gravatar.com/avatar/cb8a567bedc73c7d4a73353f8c006d82?s=128&d=identicon&r=PG", "display_name": "FastTurtle", "link": "https://stackoverflow.com/users/1507867/fastturtle"}, "creation_date": 1517270400, "down_vote_count": 0, "up_vote_count": 3, "post_id": 17684652, "question_id": 16405969, "timeline_type": "vote_aggregate"}, {"owner": {"reputation": 2714, "user_id": 7650686, "user_type": "registered", "profile_image": "https://www.gravatar.com/avatar/bbe418fb72dc9851771440b68381395f?s=128&d=identicon&r=PG&f=1", "display_name": "obgnaw", "link": "https://stackoverflow.com/users/7650686/obgnaw"}, "creation_date": 1517212532, "post_id": 48496708, "question_id": 16405969, "timeline_type": "answer"}, {"owner": {"reputation": 36633, "user_id": 533399, "user_type": "registered", "accept_rate": 95, "profile_image": "https://i.stack.imgur.com/Pem8D.jpg?s=128&g=1", "display_name": "DhruvPathak", "link": "https://stackoverflow.com/users/533399/dhruvpathak"}, "creation_date": 1517184000, "down_vote_count": 0, "up_vote_count": 1, "post_id": 16405969, "question_id": 16405969, "timeline_type": "vote_aggregate"}, {"owner": {"reputation": 36633, "user_id": 533399, "user_type": "registered", "accept_rate": 95, "profile_image": "https://i.stack.imgur.com/Pem8D.jpg?s=128&g=1", "display_name": "DhruvPathak", "link": "https://stackoverflow.com/users/533399/dhruvpathak"}, "creation_date": 1517097600, "down_vote_count": 0, "up_vote_count": 2, "post_id": 16405969, "question_id": 16405969, "timeline_type": "vote_aggregate"}, {"owner": {"reputation": 2081, "user_id": 1507867, "user_type": "registered", "profile_image": "https://www.gravatar.com/avatar/cb8a567bedc73c7d4a73353f8c006d82?s=128&d=identicon&r=PG", "display_name": "FastTurtle", "link": "https://stackoverflow.com/users/1507867/fastturtle"}, "creation_date": 1517097600, "down_vote_count": 0, "up_vote_count": 1, "post_id": 17684652, "question_id": 16405969, "timeline_type": "vote_aggregate"}, {"user": {"reputation": 5054, "user_id": 9200529, "user_type": "registered", "profile_image": "https://i.stack.imgur.com/LgIT2.jpg?s=128&g=1", "display_name": "Nathan V\u0113rzemnieks", "link": "https://stackoverflow.com/users/9200529/nathan-v%c4%93rzemnieks"}, "creation_date": 1517092349, "post_id": 48481010, "question_id": 16405969, "timeline_type": "revision", "content_license": "CC BY-SA 3.0", "revision_guid": "6B9A1D79-3131-4842-8996-D0D4245E940C"}, {"owner": {"reputation": 242459, "user_id": 674039, "user_type": "registered", "accept_rate": 94, "profile_image": "https://i.stack.imgur.com/leoFi.gif?s=128&g=1", "display_name": "wim", "link": "https://stackoverflow.com/users/674039/wim"}, "creation_date": 1517091517, "comment_id": 83955211, "post_id": 16405969, "question_id": 16405969, "timeline_type": "comment"}, {"owner": {"reputation": 5054, "user_id": 9200529, "user_type": "registered", "profile_image": "https://i.stack.imgur.com/LgIT2.jpg?s=128&g=1", "display_name": "Nathan V\u0113rzemnieks", "link": "https://stackoverflow.com/users/9200529/nathan-v%c4%93rzemnieks"}, "creation_date": 1517090482, "post_id": 48481010, "question_id": 16405969, "timeline_type": "answer"}, {"owner": {"reputation": 21136, "user_id": 2334192, "user_type": "registered", "profile_image": "https://i.stack.imgur.com/7u24l.jpg?s=128&g=1", "display_name": "James Holderness", "link": "https://stackoverflow.com/users/2334192/james-holderness"}, "creation_date": 1517011200, "down_vote_count": 0, "up_vote_count": 1, "post_id": 17798594, "question_id": 16405969, "timeline_type": "vote_aggregate"}, {"owner": {"reputation": 36633, "user_id": 533399, "user_type": "registered", "accept_rate": 95, "profile_image": "https://i.stack.imgur.com/Pem8D.jpg?s=128&g=1", "display_name": "DhruvPathak", "link": "https://stackoverflow.com/users/533399/dhruvpathak"}, "creation_date": 1516838400, "down_vote_count": 0, "up_vote_count": 2, "post_id": 16405969, "question_id": 16405969, "timeline_type": "vote_aggregate"}, {"owner": {"reputation": 115818, "user_id": 2830850, "user_type": "registered", "profile_image": "https://www.gravatar.com/avatar/e48b39b77bf324de9aeefd6c5bfc10c6?s=128&d=identicon&r=PG&f=1", "display_name": "Tarun Lalwani", "link": "https://stackoverflow.com/users/2830850/tarun-lalwani"}, "creation_date": 1516779220, "post_id": 48417068, "question_id": 16405969, "timeline_type": "answer"}, {"owner": {"reputation": 36633, "user_id": 533399, "user_type": "registered", "accept_rate": 95, "profile_image": "https://i.stack.imgur.com/Pem8D.jpg?s=128&g=1", "display_name": "DhruvPathak", "link": "https://stackoverflow.com/users/533399/dhruvpathak"}, "creation_date": 1516752000, "down_vote_count": 0, "up_vote_count": 1, "post_id": 16405969, "question_id": 16405969, "timeline_type": "vote_aggregate"}, {"owner": {"reputation": 1066, "user_id": 1838864, "user_type": "registered", "accept_rate": 46, "profile_image": "https://i.stack.imgur.com/qfWa4.jpg?s=128&g=1", "display_name": "Roy Nieterau", "link": "https://stackoverflow.com/users/1838864/roy-nieterau"}, "creation_date": 1516752000, "down_vote_count": 0, "up_vote_count": 1, "post_id": 16406798, "question_id": 16405969, "timeline_type": "vote_aggregate"}, {"owner": {"reputation": 16356, "user_id": 763269, "user_type": "registered", "accept_rate": 82, "profile_image": "https://www.gravatar.com/avatar/0c27474bcff67974d6a9fcb43cb7ba4e?s=128&d=identicon&r=PG", "display_name": "Chris Johnson", "link": "https://stackoverflow.com/users/763269/chris-johnson"}, "creation_date": 1516752000, "down_vote_count": 0, "up_vote_count": 1, "post_id": 16553841, "question_id": 16405969, "timeline_type": "vote_aggregate"}, {"owner": {"reputation": 575, "user_id": 52667, "user_type": "registered", "profile_image": "https://www.gravatar.com/avatar/ca8e570c49e971d349aaad90412d4c27?s=128&d=identicon&r=PG", "display_name": "chees", "link": "https://stackoverflow.com/users/52667/chees"}, "creation_date": 1516752000, "down_vote_count": 0, "up_vote_count": 1, "post_id": 17789421, "question_id": 16405969, "timeline_type": "vote_aggregate"}, {"owner": {"reputation": 21136, "user_id": 2334192, "user_type": "registered", "profile_image": "https://i.stack.imgur.com/7u24l.jpg?s=128&g=1", "display_name": "James Holderness", "link": "https://stackoverflow.com/users/2334192/james-holderness"}, "creation_date": 1516752000, "down_vote_count": 0, "up_vote_count": 1, "post_id": 17798594, "question_id": 16405969, "timeline_type": "vote_aggregate"}, {"owner": {"reputation": 2081, "user_id": 1507867, "user_type": "registered", "profile_image": "https://www.gravatar.com/avatar/cb8a567bedc73c7d4a73353f8c006d82?s=128&d=identicon&r=PG", "display_name": "FastTurtle", "link": "https://stackoverflow.com/users/1507867/fastturtle"}, "creation_date": 1510790400, "down_vote_count": 0, "up_vote_count": 1, "post_id": 17684652, "question_id": 16405969, "timeline_type": "vote_aggregate"}, {"owner": {"reputation": 3715, "user_id": 2355087, "user_type": "registered", "accept_rate": 100, "profile_image": "https://www.gravatar.com/avatar/9891d8ed7bb8f3deccf42058452e7e35?s=128&d=identicon&r=PG", "display_name": "marcoseu", "link": "https://stackoverflow.com/users/2355087/marcoseu"}, "creation_date": 1509408000, "down_vote_count": 1, "up_vote_count": 0, "post_id": 16471131, "question_id": 16405969, "timeline_type": "vote_aggregate"}, {"owner": {"reputation": 1066, "user_id": 1838864, "user_type": "registered", "accept_rate": 46, "profile_image": "https://i.stack.imgur.com/qfWa4.jpg?s=128&g=1", "display_name": "Roy Nieterau", "link": "https://stackoverflow.com/users/1838864/roy-nieterau"}, "creation_date": 1508544000, "down_vote_count": 0, "up_vote_count": 1, "post_id": 16406798, "question_id": 16405969, "timeline_type": "vote_aggregate"}, {"owner": {"reputation": 2081, "user_id": 1507867, "user_type": "registered", "profile_image": "https://www.gravatar.com/avatar/cb8a567bedc73c7d4a73353f8c006d82?s=128&d=identicon&r=PG", "display_name": "FastTurtle", "link": "https://stackoverflow.com/users/1507867/fastturtle"}, "creation_date": 1508544000, "down_vote_count": 0, "up_vote_count": 1, "post_id": 17684652, "question_id": 16405969, "timeline_type": "vote_aggregate"}, {"creation_date": 1495542369, "post_id": 16406798, "question_id": 16405969, "timeline_type": "revision", "content_license": "CC BY-SA 3.0", "revision_guid": "14846CA7-5266-4C7D-A1B6-AEDA2BAA1111"}, {"creation_date": 1495541875, "post_id": 17708177, "question_id": 16405969, "timeline_type": "revision", "content_license": "CC BY-SA 3.0", "revision_guid": "044D5D78-5311-4281-81F3-ECE7BCA084A8"}, {"owner": {"reputation": 1066, "user_id": 1838864, "user_type": "registered", "accept_rate": 46, "profile_image": "https://i.stack.imgur.com/qfWa4.jpg?s=128&g=1", "display_name": "Roy Nieterau", "link": "https://stackoverflow.com/users/1838864/roy-nieterau"}, "creation_date": 1494633600, "down_vote_count": 0, "up_vote_count": 1, "post_id": 16406798, "question_id": 16405969, "timeline_type": "vote_aggregate"}, {"owner": {"reputation": 2081, "user_id": 1507867, "user_type": "registered", "profile_image": "https://www.gravatar.com/avatar/cb8a567bedc73c7d4a73353f8c006d82?s=128&d=identicon&r=PG", "display_name": "FastTurtle", "link": "https://stackoverflow.com/users/1507867/fastturtle"}, "creation_date": 1494633600, "down_vote_count": 0, "up_vote_count": 1, "post_id": 17684652, "question_id": 16405969, "timeline_type": "vote_aggregate"}, {"owner": {"reputation": 36633, "user_id": 533399, "user_type": "registered", "accept_rate": 95, "profile_image": "https://i.stack.imgur.com/Pem8D.jpg?s=128&g=1", "display_name": "DhruvPathak", "link": "https://stackoverflow.com/users/533399/dhruvpathak"}, "creation_date": 1493769600, "down_vote_count": 0, "up_vote_count": 1, "post_id": 16405969, "question_id": 16405969, "timeline_type": "vote_aggregate"}, {"owner": {"reputation": 1066, "user_id": 1838864, "user_type": "registered", "accept_rate": 46, "profile_image": "https://i.stack.imgur.com/qfWa4.jpg?s=128&g=1", "display_name": "Roy Nieterau", "link": "https://stackoverflow.com/users/1838864/roy-nieterau"}, "creation_date": 1493769600, "down_vote_count": 0, "up_vote_count": 1, "post_id": 16406798, "question_id": 16405969, "timeline_type": "vote_aggregate"}, {"owner": {"reputation": 2081, "user_id": 1507867, "user_type": "registered", "profile_image": "https://www.gravatar.com/avatar/cb8a567bedc73c7d4a73353f8c006d82?s=128&d=identicon&r=PG", "display_name": "FastTurtle", "link": "https://stackoverflow.com/users/1507867/fastturtle"}, "creation_date": 1493769600, "down_vote_count": 0, "up_vote_count": 1, "post_id": 17684652, "question_id": 16405969, "timeline_type": "vote_aggregate"}, {"owner": {"reputation": 85, "user_id": 3568069, "user_type": "registered", "profile_image": "https://www.gravatar.com/avatar/41f51bbdd41211e691692affe085086c?s=128&d=identicon&r=PG", "display_name": "franzlst", "link": "https://stackoverflow.com/users/3568069/franzlst"}, "creation_date": 1491458455, "comment_id": 83851670, "post_id": 17684652, "question_id": 16405969, "timeline_type": "comment"}, {"owner": {"reputation": 36633, "user_id": 533399, "user_type": "registered", "accept_rate": 95, "profile_image": "https://i.stack.imgur.com/Pem8D.jpg?s=128&g=1", "display_name": "DhruvPathak", "link": "https://stackoverflow.com/users/533399/dhruvpathak"}, "creation_date": 1491350400, "down_vote_count": 0, "up_vote_count": 1, "post_id": 16405969, "question_id": 16405969, "timeline_type": "vote_aggregate"}, {"owner": {"reputation": 2081, "user_id": 1507867, "user_type": "registered", "profile_image": "https://www.gravatar.com/avatar/cb8a567bedc73c7d4a73353f8c006d82?s=128&d=identicon&r=PG", "display_name": "FastTurtle", "link": "https://stackoverflow.com/users/1507867/fastturtle"}, "creation_date": 1491350400, "down_vote_count": 0, "up_vote_count": 1, "post_id": 17684652, "question_id": 16405969, "timeline_type": "vote_aggregate"}, {"owner": {"reputation": 16356, "user_id": 763269, "user_type": "registered", "accept_rate": 82, "profile_image": "https://www.gravatar.com/avatar/0c27474bcff67974d6a9fcb43cb7ba4e?s=128&d=identicon&r=PG", "display_name": "Chris Johnson", "link": "https://stackoverflow.com/users/763269/chris-johnson"}, "creation_date": 1491177600, "down_vote_count": 0, "up_vote_count": 1, "post_id": 16553841, "question_id": 16405969, "timeline_type": "vote_aggregate"}, {"owner": {"reputation": 2081, "user_id": 1507867, "user_type": "registered", "profile_image": "https://www.gravatar.com/avatar/cb8a567bedc73c7d4a73353f8c006d82?s=128&d=identicon&r=PG", "display_name": "FastTurtle", "link": "https://stackoverflow.com/users/1507867/fastturtle"}, "creation_date": 1485302400, "down_vote_count": 0, "up_vote_count": 1, "post_id": 17684652, "question_id": 16405969, "timeline_type": "vote_aggregate"}, {"owner": {"reputation": 36633, "user_id": 533399, "user_type": "registered", "accept_rate": 95, "profile_image": "https://i.stack.imgur.com/Pem8D.jpg?s=128&g=1", "display_name": "DhruvPathak", "link": "https://stackoverflow.com/users/533399/dhruvpathak"}, "creation_date": 1480464000, "down_vote_count": 0, "up_vote_count": 1, "post_id": 16405969, "question_id": 16405969, "timeline_type": "vote_aggregate"}, {"user": {"reputation": 16356, "user_id": 763269, "user_type": "registered", "accept_rate": 82, "profile_image": "https://www.gravatar.com/avatar/0c27474bcff67974d6a9fcb43cb7ba4e?s=128&d=identicon&r=PG", "display_name": "Chris Johnson", "link": "https://stackoverflow.com/users/763269/chris-johnson"}, "creation_date": 1471183116, "post_id": 16553841, "question_id": 16405969, "timeline_type": "revision", "content_license": "CC BY-SA 3.0", "revision_guid": "4C1273E1-A422-40BC-9536-BE329BD594DC"}, {"owner": {"reputation": 36633, "user_id": 533399, "user_type": "registered", "accept_rate": 95, "profile_image": "https://i.stack.imgur.com/Pem8D.jpg?s=128&g=1", "display_name": "DhruvPathak", "link": "https://stackoverflow.com/users/533399/dhruvpathak"}, "creation_date": 1466035200, "down_vote_count": 0, "up_vote_count": 1, "post_id": 16405969, "question_id": 16405969, "timeline_type": "vote_aggregate"}, {"owner": {"reputation": 21136, "user_id": 2334192, "user_type": "registered", "profile_image": "https://i.stack.imgur.com/7u24l.jpg?s=128&g=1", "display_name": "James Holderness", "link": "https://stackoverflow.com/users/2334192/james-holderness"}, "creation_date": 1466035200, "down_vote_count": 0, "up_vote_count": 1, "post_id": 17798594, "question_id": 16405969, "timeline_type": "vote_aggregate"}, {"owner": {"reputation": 36633, "user_id": 533399, "user_type": "registered", "accept_rate": 95, "profile_image": "https://i.stack.imgur.com/Pem8D.jpg?s=128&g=1", "display_name": "DhruvPathak", "link": "https://stackoverflow.com/users/533399/dhruvpathak"}, "creation_date": 1459209600, "down_vote_count": 0, "up_vote_count": 1, "post_id": 16405969, "question_id": 16405969, "timeline_type": "vote_aggregate"}, {"owner": {"reputation": 2081, "user_id": 1507867, "user_type": "registered", "profile_image": "https://www.gravatar.com/avatar/cb8a567bedc73c7d4a73353f8c006d82?s=128&d=identicon&r=PG", "display_name": "FastTurtle", "link": "https://stackoverflow.com/users/1507867/fastturtle"}, "creation_date": 1454630400, "down_vote_count": 0, "up_vote_count": 1, "post_id": 17684652, "question_id": 16405969, "timeline_type": "vote_aggregate"}, {"owner": {"reputation": 2081, "user_id": 1507867, "user_type": "registered", "profile_image": "https://www.gravatar.com/avatar/cb8a567bedc73c7d4a73353f8c006d82?s=128&d=identicon&r=PG", "display_name": "FastTurtle", "link": "https://stackoverflow.com/users/1507867/fastturtle"}, "creation_date": 1453507200, "down_vote_count": 0, "up_vote_count": 1, "post_id": 17684652, "question_id": 16405969, "timeline_type": "vote_aggregate"}, {"owner": {"reputation": 36633, "user_id": 533399, "user_type": "registered", "accept_rate": 95, "profile_image": "https://i.stack.imgur.com/Pem8D.jpg?s=128&g=1", "display_name": "DhruvPathak", "link": "https://stackoverflow.com/users/533399/dhruvpathak"}, "creation_date": 1444953600, "down_vote_count": 0, "up_vote_count": 1, "post_id": 16405969, "question_id": 16405969, "timeline_type": "vote_aggregate"}, {"owner": {"reputation": 27675, "user_id": 402884, "user_type": "registered", "accept_rate": 75, "profile_image": "https://www.gravatar.com/avatar/35583fe46c2cde92467710cc7ceff266?s=128&d=identicon&r=PG", "display_name": "Chris Martin", "link": "https://stackoverflow.com/users/402884/chris-martin"}, "creation_date": 1441432531, "comment_id": 52687689, "post_id": 17779373, "question_id": 16405969, "timeline_type": "comment"}, {"owner": {"reputation": 1322, "user_id": 2574559, "user_type": "registered", "profile_image": "https://www.gravatar.com/avatar/0930eaece1635bab8e35a5fb9dfc1739?s=128&d=identicon&r=PG", "display_name": "bks", "link": "https://stackoverflow.com/users/2574559/bks"}, "creation_date": 1441411200, "down_vote_count": 1, "up_vote_count": 0, "post_id": 17779373, "question_id": 16405969, "timeline_type": "vote_aggregate"}, {"owner": {"reputation": 2081, "user_id": 1507867, "user_type": "registered", "profile_image": "https://www.gravatar.com/avatar/cb8a567bedc73c7d4a73353f8c006d82?s=128&d=identicon&r=PG", "display_name": "FastTurtle", "link": "https://stackoverflow.com/users/1507867/fastturtle"}, "creation_date": 1430092800, "down_vote_count": 0, "up_vote_count": 1, "post_id": 17684652, "question_id": 16405969, "timeline_type": "vote_aggregate"}, {"owner": {"reputation": 3795, "user_id": 4342563, "user_type": "registered", "accept_rate": 57, "profile_image": "https://i.stack.imgur.com/xgGSM.png?s=128&g=1", "display_name": "Eric Lease", "link": "https://stackoverflow.com/users/4342563/eric-lease"}, "creation_date": 1429253327, "comment_id": 47520841, "post_id": 16405969, "question_id": 16405969, "timeline_type": "comment"}, {"owner": {"reputation": 36633, "user_id": 533399, "user_type": "registered", "accept_rate": 95, "profile_image": "https://i.stack.imgur.com/Pem8D.jpg?s=128&g=1", "display_name": "DhruvPathak", "link": "https://stackoverflow.com/users/533399/dhruvpathak"}, "creation_date": 1429228800, "down_vote_count": 0, "up_vote_count": 6, "post_id": 16405969, "question_id": 16405969, "timeline_type": "vote_aggregate"}, {"owner": {"reputation": 1066, "user_id": 1838864, "user_type": "registered", "accept_rate": 46, "profile_image": "https://i.stack.imgur.com/qfWa4.jpg?s=128&g=1", "display_name": "Roy Nieterau", "link": "https://stackoverflow.com/users/1838864/roy-nieterau"}, "creation_date": 1429228800, "down_vote_count": 0, "up_vote_count": 1, "post_id": 16406798, "question_id": 16405969, "timeline_type": "vote_aggregate"}, {"owner": {"reputation": 2081, "user_id": 1507867, "user_type": "registered", "profile_image": "https://www.gravatar.com/avatar/cb8a567bedc73c7d4a73353f8c006d82?s=128&d=identicon&r=PG", "display_name": "FastTurtle", "link": "https://stackoverflow.com/users/1507867/fastturtle"}, "creation_date": 1429228800, "down_vote_count": 0, "up_vote_count": 1, "post_id": 17684652, "question_id": 16405969, "timeline_type": "vote_aggregate"}, {"owner": {"reputation": 36633, "user_id": 533399, "user_type": "registered", "accept_rate": 95, "profile_image": "https://i.stack.imgur.com/Pem8D.jpg?s=128&g=1", "display_name": "DhruvPathak", "link": "https://stackoverflow.com/users/533399/dhruvpathak"}, "creation_date": 1429142400, "down_vote_count": 0, "up_vote_count": 5, "post_id": 16405969, "question_id": 16405969, "timeline_type": "vote_aggregate"}, {"owner": {"reputation": 1066, "user_id": 1838864, "user_type": "registered", "accept_rate": 46, "profile_image": "https://i.stack.imgur.com/qfWa4.jpg?s=128&g=1", "display_name": "Roy Nieterau", "link": "https://stackoverflow.com/users/1838864/roy-nieterau"}, "creation_date": 1429142400, "down_vote_count": 0, "up_vote_count": 2, "post_id": 16406798, "question_id": 16405969, "timeline_type": "vote_aggregate"}, {"owner": {"reputation": 2081, "user_id": 1507867, "user_type": "registered", "profile_image": "https://www.gravatar.com/avatar/cb8a567bedc73c7d4a73353f8c006d82?s=128&d=identicon&r=PG", "display_name": "FastTurtle", "link": "https://stackoverflow.com/users/1507867/fastturtle"}, "creation_date": 1429142400, "down_vote_count": 0, "up_vote_count": 3, "post_id": 17684652, "question_id": 16405969, "timeline_type": "vote_aggregate"}, {"owner": {"reputation": 21136, "user_id": 2334192, "user_type": "registered", "profile_image": "https://i.stack.imgur.com/7u24l.jpg?s=128&g=1", "display_name": "James Holderness", "link": "https://stackoverflow.com/users/2334192/james-holderness"}, "creation_date": 1429142400, "down_vote_count": 0, "up_vote_count": 1, "post_id": 17798594, "question_id": 16405969, "timeline_type": "vote_aggregate"}, {"owner": {"reputation": 36633, "user_id": 533399, "user_type": "registered", "accept_rate": 95, "profile_image": "https://i.stack.imgur.com/Pem8D.jpg?s=128&g=1", "display_name": "DhruvPathak", "link": "https://stackoverflow.com/users/533399/dhruvpathak"}, "creation_date": 1429056000, "down_vote_count": 0, "up_vote_count": 1, "post_id": 16405969, "question_id": 16405969, "timeline_type": "vote_aggregate"}, {"owner": {"reputation": 2081, "user_id": 1507867, "user_type": "registered", "profile_image": "https://www.gravatar.com/avatar/cb8a567bedc73c7d4a73353f8c006d82?s=128&d=identicon&r=PG", "display_name": "FastTurtle", "link": "https://stackoverflow.com/users/1507867/fastturtle"}, "creation_date": 1429056000, "down_vote_count": 0, "up_vote_count": 2, "post_id": 17684652, "question_id": 16405969, "timeline_type": "vote_aggregate"}, {"owner": {"reputation": 36633, "user_id": 533399, "user_type": "registered", "accept_rate": 95, "profile_image": "https://i.stack.imgur.com/Pem8D.jpg?s=128&g=1", "display_name": "DhruvPathak", "link": "https://stackoverflow.com/users/533399/dhruvpathak"}, "creation_date": 1428883200, "down_vote_count": 0, "up_vote_count": 1, "post_id": 16405969, "question_id": 16405969, "timeline_type": "vote_aggregate"}, {"owner": {"reputation": 2081, "user_id": 1507867, "user_type": "registered", "profile_image": "https://www.gravatar.com/avatar/cb8a567bedc73c7d4a73353f8c006d82?s=128&d=identicon&r=PG", "display_name": "FastTurtle", "link": "https://stackoverflow.com/users/1507867/fastturtle"}, "creation_date": 1428883200, "down_vote_count": 0, "up_vote_count": 1, "post_id": 17684652, "question_id": 16405969, "timeline_type": "vote_aggregate"}, {"owner": {"reputation": 16356, "user_id": 763269, "user_type": "registered", "accept_rate": 82, "profile_image": "https://www.gravatar.com/avatar/0c27474bcff67974d6a9fcb43cb7ba4e?s=128&d=identicon&r=PG", "display_name": "Chris Johnson", "link": "https://stackoverflow.com/users/763269/chris-johnson"}, "creation_date": 1398816000, "down_vote_count": 0, "up_vote_count": 1, "post_id": 16553841, "question_id": 16405969, "timeline_type": "vote_aggregate"}, {"owner": {"reputation": 21423, "user_id": 1733117, "user_type": "registered", "profile_image": "https://www.gravatar.com/avatar/5b886d4df174af783771e8a4dbaa4bf7?s=128&d=identicon&r=PG", "display_name": "dnozay", "link": "https://stackoverflow.com/users/1733117/dnozay"}, "creation_date": 1390780800, "down_vote_count": 0, "up_vote_count": 1, "post_id": 17708177, "question_id": 16405969, "timeline_type": "vote_aggregate"}, {"user": {"reputation": 1066, "user_id": 1838864, "user_type": "registered", "accept_rate": 46, "profile_image": "https://i.stack.imgur.com/qfWa4.jpg?s=128&g=1", "display_name": "Roy Nieterau", "link": "https://stackoverflow.com/users/1838864/roy-nieterau"}, "creation_date": 1385473220, "post_id": 16406798, "question_id": 16405969, "timeline_type": "revision", "content_license": "CC BY-SA 3.0", "revision_guid": "FB26C850-3633-4CD4-A263-EEAE290A4B32"}, {"owner": {"reputation": 2081, "user_id": 1507867, "user_type": "registered", "profile_image": "https://www.gravatar.com/avatar/cb8a567bedc73c7d4a73353f8c006d82?s=128&d=identicon&r=PG", "display_name": "FastTurtle", "link": "https://stackoverflow.com/users/1507867/fastturtle"}, "creation_date": 1385424000, "down_vote_count": 0, "up_vote_count": 1, "post_id": 17684652, "question_id": 16405969, "timeline_type": "vote_aggregate"}, {"owner": {"reputation": 36633, "user_id": 533399, "user_type": "registered", "accept_rate": 95, "profile_image": "https://i.stack.imgur.com/Pem8D.jpg?s=128&g=1", "display_name": "DhruvPathak", "link": "https://stackoverflow.com/users/533399/dhruvpathak"}, "creation_date": 1374537600, "down_vote_count": 0, "up_vote_count": 2, "post_id": 16405969, "question_id": 16405969, "timeline_type": "vote_aggregate"}, {"owner": {"reputation": 1066, "user_id": 1838864, "user_type": "registered", "accept_rate": 46, "profile_image": "https://i.stack.imgur.com/qfWa4.jpg?s=128&g=1", "display_name": "Roy Nieterau", "link": "https://stackoverflow.com/users/1838864/roy-nieterau"}, "creation_date": 1374537600, "down_vote_count": 0, "up_vote_count": 1, "post_id": 16406798, "question_id": 16405969, "timeline_type": "vote_aggregate"}, {"owner": {"reputation": 3715, "user_id": 2355087, "user_type": "registered", "accept_rate": 100, "profile_image": "https://www.gravatar.com/avatar/9891d8ed7bb8f3deccf42058452e7e35?s=128&d=identicon&r=PG", "display_name": "marcoseu", "link": "https://stackoverflow.com/users/2355087/marcoseu"}, "creation_date": 1374537600, "down_vote_count": 0, "up_vote_count": 1, "post_id": 16471131, "question_id": 16405969, "timeline_type": "vote_aggregate"}, {"owner": {"reputation": 16356, "user_id": 763269, "user_type": "registered", "accept_rate": 82, "profile_image": "https://www.gravatar.com/avatar/0c27474bcff67974d6a9fcb43cb7ba4e?s=128&d=identicon&r=PG", "display_name": "Chris Johnson", "link": "https://stackoverflow.com/users/763269/chris-johnson"}, "creation_date": 1374537600, "down_vote_count": 0, "up_vote_count": 1, "post_id": 16553841, "question_id": 16405969, "timeline_type": "vote_aggregate"}, {"owner": {"reputation": 2081, "user_id": 1507867, "user_type": "registered", "profile_image": "https://www.gravatar.com/avatar/cb8a567bedc73c7d4a73353f8c006d82?s=128&d=identicon&r=PG", "display_name": "FastTurtle", "link": "https://stackoverflow.com/users/1507867/fastturtle"}, "creation_date": 1374537600, "down_vote_count": 0, "up_vote_count": 1, "post_id": 17684652, "question_id": 16405969, "timeline_type": "vote_aggregate"}, {"owner": {"reputation": 3182, "user_id": 1243064, "user_type": "registered", "accept_rate": 80, "profile_image": "https://www.gravatar.com/avatar/cfd730a0226e5295824a0a1d9224af24?s=128&d=identicon&r=PG", "display_name": "Wessie", "link": "https://stackoverflow.com/users/1243064/wessie"}, "creation_date": 1374537600, "down_vote_count": 0, "up_vote_count": 1, "post_id": 17685236, "question_id": 16405969, "timeline_type": "vote_aggregate"}, {"owner": {"reputation": 21423, "user_id": 1733117, "user_type": "registered", "profile_image": "https://www.gravatar.com/avatar/5b886d4df174af783771e8a4dbaa4bf7?s=128&d=identicon&r=PG", "display_name": "dnozay", "link": "https://stackoverflow.com/users/1733117/dnozay"}, "creation_date": 1374537600, "down_vote_count": 0, "up_vote_count": 1, "post_id": 17708177, "question_id": 16405969, "timeline_type": "vote_aggregate"}, {"owner": {"reputation": 1322, "user_id": 2574559, "user_type": "registered", "profile_image": "https://www.gravatar.com/avatar/0930eaece1635bab8e35a5fb9dfc1739?s=128&d=identicon&r=PG", "display_name": "bks", "link": "https://stackoverflow.com/users/2574559/bks"}, "creation_date": 1374537600, "down_vote_count": 0, "up_vote_count": 3, "post_id": 17779373, "question_id": 16405969, "timeline_type": "vote_aggregate"}, {"owner": {"reputation": 575, "user_id": 52667, "user_type": "registered", "profile_image": "https://www.gravatar.com/avatar/ca8e570c49e971d349aaad90412d4c27?s=128&d=identicon&r=PG", "display_name": "chees", "link": "https://stackoverflow.com/users/52667/chees"}, "creation_date": 1374537600, "down_vote_count": 0, "up_vote_count": 1, "post_id": 17789421, "question_id": 16405969, "timeline_type": "vote_aggregate"}, {"owner": {"reputation": 21136, "user_id": 2334192, "user_type": "registered", "profile_image": "https://i.stack.imgur.com/7u24l.jpg?s=128&g=1", "display_name": "James Holderness", "link": "https://stackoverflow.com/users/2334192/james-holderness"}, "creation_date": 1374537600, "down_vote_count": 0, "up_vote_count": 2, "post_id": 17798594, "question_id": 16405969, "timeline_type": "vote_aggregate"}, {"owner": {"reputation": 21136, "user_id": 2334192, "user_type": "registered", "profile_image": "https://i.stack.imgur.com/7u24l.jpg?s=128&g=1", "display_name": "James Holderness", "link": "https://stackoverflow.com/users/2334192/james-holderness"}, "creation_date": 1374532370, "post_id": 17798594, "question_id": 16405969, "timeline_type": "answer"}, {"owner": {"reputation": 575, "user_id": 52667, "user_type": "registered", "profile_image": "https://www.gravatar.com/avatar/ca8e570c49e971d349aaad90412d4c27?s=128&d=identicon&r=PG", "display_name": "chees", "link": "https://stackoverflow.com/users/52667/chees"}, "creation_date": 1374501333, "post_id": 17789421, "question_id": 16405969, "timeline_type": "answer"}, {"owner": {"reputation": 1322, "user_id": 2574559, "user_type": "registered", "profile_image": "https://www.gravatar.com/avatar/0930eaece1635bab8e35a5fb9dfc1739?s=128&d=identicon&r=PG", "display_name": "bks", "link": "https://stackoverflow.com/users/2574559/bks"}, "creation_date": 1374462784, "post_id": 17779373, "question_id": 16405969, "timeline_type": "answer"}, {"owner": {"reputation": 36633, "user_id": 533399, "user_type": "registered", "accept_rate": 95, "profile_image": "https://i.stack.imgur.com/Pem8D.jpg?s=128&g=1", "display_name": "DhruvPathak", "link": "https://stackoverflow.com/users/533399/dhruvpathak"}, "creation_date": 1374364800, "down_vote_count": 0, "up_vote_count": 2, "post_id": 16405969, "question_id": 16405969, "timeline_type": "vote_aggregate"}, {"owner": {"reputation": 36633, "user_id": 533399, "user_type": "registered", "accept_rate": 95, "profile_image": "https://i.stack.imgur.com/Pem8D.jpg?s=128&g=1", "display_name": "DhruvPathak", "link": "https://stackoverflow.com/users/533399/dhruvpathak"}, "creation_date": 1374192000, "down_vote_count": 0, "up_vote_count": 1, "post_id": 16405969, "question_id": 16405969, "timeline_type": "vote_aggregate"}, {"owner": {"reputation": 1066, "user_id": 1838864, "user_type": "registered", "accept_rate": 46, "profile_image": "https://i.stack.imgur.com/qfWa4.jpg?s=128&g=1", "display_name": "Roy Nieterau", "link": "https://stackoverflow.com/users/1838864/roy-nieterau"}, "creation_date": 1374192000, "down_vote_count": 0, "up_vote_count": 1, "post_id": 16406798, "question_id": 16405969, "timeline_type": "vote_aggregate"}, {"owner": {"reputation": 21423, "user_id": 1733117, "user_type": "registered", "profile_image": "https://www.gravatar.com/avatar/5b886d4df174af783771e8a4dbaa4bf7?s=128&d=identicon&r=PG", "display_name": "dnozay", "link": "https://stackoverflow.com/users/1733117/dnozay"}, "creation_date": 1374087931, "post_id": 17708177, "question_id": 16405969, "timeline_type": "answer"}, {"owner": {"reputation": 36633, "user_id": 533399, "user_type": "registered", "accept_rate": 95, "profile_image": "https://i.stack.imgur.com/Pem8D.jpg?s=128&g=1", "display_name": "DhruvPathak", "link": "https://stackoverflow.com/users/533399/dhruvpathak"}, "creation_date": 1374019200, "down_vote_count": 0, "up_vote_count": 1, "post_id": 16405969, "question_id": 16405969, "timeline_type": "vote_aggregate"}, {"owner": {"reputation": 3182, "user_id": 1243064, "user_type": "registered", "accept_rate": 80, "profile_image": "https://www.gravatar.com/avatar/cfd730a0226e5295824a0a1d9224af24?s=128&d=identicon&r=PG", "display_name": "Wessie", "link": "https://stackoverflow.com/users/1243064/wessie"}, "creation_date": 1374002466, "post_id": 17685236, "question_id": 16405969, "timeline_type": "answer"}, {"owner": {"reputation": 2081, "user_id": 1507867, "user_type": "registered", "profile_image": "https://www.gravatar.com/avatar/cb8a567bedc73c7d4a73353f8c006d82?s=128&d=identicon&r=PG", "display_name": "FastTurtle", "link": "https://stackoverflow.com/users/1507867/fastturtle"}, "creation_date": 1374000586, "post_id": 17684652, "question_id": 16405969, "timeline_type": "answer"}, {"owner": {"reputation": 36633, "user_id": 533399, "user_type": "registered", "accept_rate": 95, "profile_image": "https://i.stack.imgur.com/Pem8D.jpg?s=128&g=1", "display_name": "DhruvPathak", "link": "https://stackoverflow.com/users/533399/dhruvpathak"}, "creation_date": 1373932800, "down_vote_count": 0, "up_vote_count": 3, "post_id": 16405969, "question_id": 16405969, "timeline_type": "vote_aggregate"}, {"owner": {"reputation": 2081, "user_id": 1507867, "user_type": "registered", "profile_image": "https://www.gravatar.com/avatar/cb8a567bedc73c7d4a73353f8c006d82?s=128&d=identicon&r=PG", "display_name": "FastTurtle", "link": "https://stackoverflow.com/users/1507867/fastturtle"}, "creation_date": 1373932800, "down_vote_count": 0, "up_vote_count": 1, "post_id": 17684652, "question_id": 16405969, "timeline_type": "vote_aggregate"}, {"owner": {"reputation": 36633, "user_id": 533399, "user_type": "registered", "accept_rate": 95, "profile_image": "https://i.stack.imgur.com/Pem8D.jpg?s=128&g=1", "display_name": "DhruvPathak", "link": "https://stackoverflow.com/users/533399/dhruvpathak"}, "creation_date": 1370304000, "down_vote_count": 0, "up_vote_count": 1, "post_id": 16405969, "question_id": 16405969, "timeline_type": "vote_aggregate"}, {"owner": {"reputation": 36633, "user_id": 533399, "user_type": "registered", "accept_rate": 95, "profile_image": "https://i.stack.imgur.com/Pem8D.jpg?s=128&g=1", "display_name": "DhruvPathak", "link": "https://stackoverflow.com/users/533399/dhruvpathak"}, "creation_date": 1370044800, "down_vote_count": 0, "up_vote_count": 1, "post_id": 16405969, "question_id": 16405969, "timeline_type": "vote_aggregate"}, {"user": {"reputation": 16356, "user_id": 763269, "user_type": "registered", "accept_rate": 82, "profile_image": "https://www.gravatar.com/avatar/0c27474bcff67974d6a9fcb43cb7ba4e?s=128&d=identicon&r=PG", "display_name": "Chris Johnson", "link": "https://stackoverflow.com/users/763269/chris-johnson"}, "creation_date": 1369794027, "post_id": 16553841, "question_id": 16405969, "timeline_type": "revision", "content_license": "CC BY-SA 3.0", "revision_guid": "C2619D9E-BD32-4D35-A717-4F31DDC65B52"}, {"user": {"reputation": 1450, "user_id": 1353248, "user_type": "registered", "profile_image": "https://www.gravatar.com/avatar/76f2159e2379729ff6668f18df1afff8?s=128&d=identicon&r=PG", "display_name": "Vairis", "link": "https://stackoverflow.com/users/1353248/vairis"}, "creation_date": 1369754187, "post_id": 16405969, "question_id": 16405969, "timeline_type": "revision", "content_license": "CC BY-SA 3.0", "revision_guid": "0C283690-0405-4305-B13A-5B214E73545F"}, {"owner": {"reputation": 36633, "user_id": 533399, "user_type": "registered", "accept_rate": 95, "profile_image": "https://i.stack.imgur.com/Pem8D.jpg?s=128&g=1", "display_name": "DhruvPathak", "link": "https://stackoverflow.com/users/533399/dhruvpathak"}, "creation_date": 1369699200, "down_vote_count": 0, "up_vote_count": 5, "post_id": 16405969, "question_id": 16405969, "timeline_type": "vote_aggregate"}, {"owner": {"reputation": 16356, "user_id": 763269, "user_type": "registered", "accept_rate": 82, "profile_image": "https://www.gravatar.com/avatar/0c27474bcff67974d6a9fcb43cb7ba4e?s=128&d=identicon&r=PG", "display_name": "Chris Johnson", "link": "https://stackoverflow.com/users/763269/chris-johnson"}, "creation_date": 1369699200, "down_vote_count": 0, "up_vote_count": 1, "post_id": 16553841, "question_id": 16405969, "timeline_type": "vote_aggregate"}, {"owner": {"reputation": 36633, "user_id": 533399, "user_type": "registered", "accept_rate": 95, "profile_image": "https://i.stack.imgur.com/Pem8D.jpg?s=128&g=1", "display_name": "DhruvPathak", "link": "https://stackoverflow.com/users/533399/dhruvpathak"}, "creation_date": 1369612800, "down_vote_count": 0, "up_vote_count": 1, "post_id": 16405969, "question_id": 16405969, "timeline_type": "vote_aggregate"}, {"user": {"reputation": 16356, "user_id": 763269, "user_type": "registered", "accept_rate": 82, "profile_image": "https://www.gravatar.com/avatar/0c27474bcff67974d6a9fcb43cb7ba4e?s=128&d=identicon&r=PG", "display_name": "Chris Johnson", "link": "https://stackoverflow.com/users/763269/chris-johnson"}, "creation_date": 1368695776, "post_id": 16553841, "question_id": 16405969, "timeline_type": "revision", "content_license": "CC BY-SA 3.0", "revision_guid": "BB41A2E0-4AA9-4D5F-B95F-46B6DE4CA02B"}, {"owner": {"reputation": 36633, "user_id": 533399, "user_type": "registered", "accept_rate": 95, "profile_image": "https://i.stack.imgur.com/Pem8D.jpg?s=128&g=1", "display_name": "DhruvPathak", "link": "https://stackoverflow.com/users/533399/dhruvpathak"}, "creation_date": 1368687129, "comment_id": 23827421, "post_id": 16471131, "question_id": 16405969, "timeline_type": "comment"}, {"owner": {"reputation": 36633, "user_id": 533399, "user_type": "registered", "accept_rate": 95, "profile_image": "https://i.stack.imgur.com/Pem8D.jpg?s=128&g=1", "display_name": "DhruvPathak", "link": "https://stackoverflow.com/users/533399/dhruvpathak"}, "creation_date": 1368598607, "comment_id": 23788000, "post_id": 16553841, "question_id": 16405969, "timeline_type": "comment"}, {"owner": {"reputation": 36633, "user_id": 533399, "user_type": "registered", "accept_rate": 95, "profile_image": "https://i.stack.imgur.com/Pem8D.jpg?s=128&g=1", "display_name": "DhruvPathak", "link": "https://stackoverflow.com/users/533399/dhruvpathak"}, "creation_date": 1368576000, "down_vote_count": 0, "up_vote_count": 2, "post_id": 16405969, "question_id": 16405969, "timeline_type": "vote_aggregate"}, {"owner": {"reputation": 16356, "user_id": 763269, "user_type": "registered", "accept_rate": 82, "profile_image": "https://www.gravatar.com/avatar/0c27474bcff67974d6a9fcb43cb7ba4e?s=128&d=identicon&r=PG", "display_name": "Chris Johnson", "link": "https://stackoverflow.com/users/763269/chris-johnson"}, "creation_date": 1368570263, "post_id": 16553841, "question_id": 16405969, "timeline_type": "answer"}, {"user": {"reputation": 3715, "user_id": 2355087, "user_type": "registered", "accept_rate": 100, "profile_image": "https://www.gravatar.com/avatar/9891d8ed7bb8f3deccf42058452e7e35?s=128&d=identicon&r=PG", "display_name": "marcoseu", "link": "https://stackoverflow.com/users/2355087/marcoseu"}, "creation_date": 1368136574, "post_id": 16471131, "question_id": 16405969, "timeline_type": "revision", "content_license": "CC BY-SA 3.0", "revision_guid": "68F355C3-233A-4F7E-A28A-ACC1809A9D67"}, {"user": {"reputation": 3715, "user_id": 2355087, "user_type": "registered", "accept_rate": 100, "profile_image": "https://www.gravatar.com/avatar/9891d8ed7bb8f3deccf42058452e7e35?s=128&d=identicon&r=PG", "display_name": "marcoseu", "link": "https://stackoverflow.com/users/2355087/marcoseu"}, "creation_date": 1368135160, "post_id": 16471131, "question_id": 16405969, "timeline_type": "revision", "content_license": "CC BY-SA 3.0", "revision_guid": "CF55F40E-EA5E-4A70-9953-11385AF0243D"}, {"owner": {"reputation": 3715, "user_id": 2355087, "user_type": "registered", "accept_rate": 100, "profile_image": "https://www.gravatar.com/avatar/9891d8ed7bb8f3deccf42058452e7e35?s=128&d=identicon&r=PG", "display_name": "marcoseu", "link": "https://stackoverflow.com/users/2355087/marcoseu"}, "creation_date": 1368133616, "post_id": 16471131, "question_id": 16405969, "timeline_type": "answer"}, {"user": {"reputation": 36633, "user_id": 533399, "user_type": "registered", "accept_rate": 95, "profile_image": "https://i.stack.imgur.com/Pem8D.jpg?s=128&g=1", "display_name": "DhruvPathak", "link": "https://stackoverflow.com/users/533399/dhruvpathak"}, "creation_date": 1368078276, "post_id": 16405969, "question_id": 16405969, "timeline_type": "revision", "content_license": "CC BY-SA 3.0", "revision_guid": "AD076A4B-7F3F-4557-AD5E-9157D52189B6"}, {"owner": {"reputation": 36633, "user_id": 533399, "user_type": "registered", "accept_rate": 95, "profile_image": "https://i.stack.imgur.com/Pem8D.jpg?s=128&g=1", "display_name": "DhruvPathak", "link": "https://stackoverflow.com/users/533399/dhruvpathak"}, "creation_date": 1368057600, "down_vote_count": 0, "up_vote_count": 1, "post_id": 16405969, "question_id": 16405969, "timeline_type": "vote_aggregate"}, {"owner": {"reputation": 3715, "user_id": 2355087, "user_type": "registered", "accept_rate": 100, "profile_image": "https://www.gravatar.com/avatar/9891d8ed7bb8f3deccf42058452e7e35?s=128&d=identicon&r=PG", "display_name": "marcoseu", "link": "https://stackoverflow.com/users/2355087/marcoseu"}, "creation_date": 1368057600, "down_vote_count": 0, "up_vote_count": 1, "post_id": 16471131, "question_id": 16405969, "timeline_type": "vote_aggregate"}, {"owner": {"reputation": 36633, "user_id": 533399, "user_type": "registered", "accept_rate": 95, "profile_image": "https://i.stack.imgur.com/Pem8D.jpg?s=128&g=1", "display_name": "DhruvPathak", "link": "https://stackoverflow.com/users/533399/dhruvpathak"}, "creation_date": 1368000165, "comment_id": 23571408, "post_id": 16406798, "question_id": 16405969, "timeline_type": "comment"}, {"user": {"reputation": 36633, "user_id": 533399, "user_type": "registered", "accept_rate": 95, "profile_image": "https://i.stack.imgur.com/Pem8D.jpg?s=128&g=1", "display_name": "DhruvPathak", "link": "https://stackoverflow.com/users/533399/dhruvpathak"}, "creation_date": 1367914712, "post_id": 16405969, "question_id": 16405969, "timeline_type": "revision", "content_license": "CC BY-SA 3.0", "revision_guid": "B9D49618-CC66-43E1-B59F-473BD38E5FDE"}, {"owner": {"reputation": 36633, "user_id": 533399, "user_type": "registered", "accept_rate": 95, "profile_image": "https://i.stack.imgur.com/Pem8D.jpg?s=128&g=1", "display_name": "DhruvPathak", "link": "https://stackoverflow.com/users/533399/dhruvpathak"}, "creation_date": 1367884800, "down_vote_count": 0, "up_vote_count": 1, "post_id": 16405969, "question_id": 16405969, "timeline_type": "vote_aggregate"}, {"user": {"reputation": 1066, "user_id": 1838864, "user_type": "registered", "accept_rate": 46, "profile_image": "https://i.stack.imgur.com/qfWa4.jpg?s=128&g=1", "display_name": "Roy Nieterau", "link": "https://stackoverflow.com/users/1838864/roy-nieterau"}, "creation_date": 1367873624, "post_id": 16406798, "question_id": 16405969, "timeline_type": "revision", "content_license": "CC BY-SA 3.0", "revision_guid": "76AFEBB7-1BAF-46C6-B845-C9CB25FFC346"}, {"user": {"reputation": 1066, "user_id": 1838864, "user_type": "registered", "accept_rate": 46, "profile_image": "https://i.stack.imgur.com/qfWa4.jpg?s=128&g=1", "display_name": "Roy Nieterau", "link": "https://stackoverflow.com/users/1838864/roy-nieterau"}, "creation_date": 1367873309, "post_id": 16406798, "question_id": 16405969, "timeline_type": "revision", "content_license": "CC BY-SA 3.0", "revision_guid": "F987CF16-BAC7-4F2C-9C18-F2699B3E8F5A"}, {"owner": {"reputation": 1066, "user_id": 1838864, "user_type": "registered", "accept_rate": 46, "profile_image": "https://i.stack.imgur.com/qfWa4.jpg?s=128&g=1", "display_name": "Roy Nieterau", "link": "https://stackoverflow.com/users/1838864/roy-nieterau"}, "creation_date": 1367872326, "post_id": 16406798, "question_id": 16405969, "timeline_type": "answer"}, {"owner": {"reputation": 840839, "user_id": 100297, "user_type": "moderator", "profile_image": "https://www.gravatar.com/avatar/24780fb6df85a943c7aea0402c843737?s=128&d=identicon&r=PG", "display_name": "Martijn Pieters", "link": "https://stackoverflow.com/users/100297/martijn-pieters"}, "creation_date": 1367869698, "comment_id": 23520331, "post_id": 16405969, "question_id": 16405969, "timeline_type": "comment"}, {"user": {"reputation": 36633, "user_id": 533399, "user_type": "registered", "accept_rate": 95, "profile_image": "https://i.stack.imgur.com/Pem8D.jpg?s=128&g=1", "display_name": "DhruvPathak", "link": "https://stackoverflow.com/users/533399/dhruvpathak"}, "creation_date": 1367869689, "post_id": 16405969, "question_id": 16405969, "timeline_type": "revision", "content_license": "CC BY-SA 3.0", "revision_guid": "DA20962D-7DB9-40F9-9EC3-AF47BCF6FCF7"}, {"owner": {"reputation": 1066, "user_id": 1838864, "user_type": "registered", "accept_rate": 46, "profile_image": "https://i.stack.imgur.com/qfWa4.jpg?s=128&g=1", "display_name": "Roy Nieterau", "link": "https://stackoverflow.com/users/1838864/roy-nieterau"}, "creation_date": 1367869594, "comment_id": 23520288, "post_id": 16405969, "question_id": 16405969, "timeline_type": "comment"}, {"owner": {"reputation": 36633, "user_id": 533399, "user_type": "registered", "accept_rate": 95, "profile_image": "https://i.stack.imgur.com/Pem8D.jpg?s=128&g=1", "display_name": "DhruvPathak", "link": "https://stackoverflow.com/users/533399/dhruvpathak"}, "creation_date": 1367869589, "comment_id": 23520285, "post_id": 16405969, "question_id": 16405969, "timeline_type": "comment"}, {"owner": {"reputation": 840839, "user_id": 100297, "user_type": "moderator", "profile_image": "https://www.gravatar.com/avatar/24780fb6df85a943c7aea0402c843737?s=128&d=identicon&r=PG", "display_name": "Martijn Pieters", "link": "https://stackoverflow.com/users/100297/martijn-pieters"}, "creation_date": 1367869493, "comment_id": 23520233, "post_id": 16405969, "question_id": 16405969, "timeline_type": "comment"}, {"owner": {"reputation": 323300, "user_id": 139010, "user_type": "registered", "accept_rate": 81, "profile_image": "https://www.gravatar.com/avatar/0df2f3c2d3b43605889eb90231fb6884?s=128&d=identicon&r=PG", "display_name": "Matt Ball", "link": "https://stackoverflow.com/users/139010/matt-ball"}, "creation_date": 1367869330, "comment_id": 23520150, "post_id": 16405969, "question_id": 16405969, "timeline_type": "comment"}, {"owner": {"reputation": 36633, "user_id": 533399, "user_type": "registered", "accept_rate": 95, "profile_image": "https://i.stack.imgur.com/Pem8D.jpg?s=128&g=1", "display_name": "DhruvPathak", "link": "https://stackoverflow.com/users/533399/dhruvpathak"}, "creation_date": 1367869171, "question_id": 16405969, "timeline_type": "question"}, {"owner": {"reputation": 1066, "user_id": 1838864, "user_type": "registered", "accept_rate": 46, "profile_image": "https://i.stack.imgur.com/qfWa4.jpg?s=128&g=1", "display_name": "Roy Nieterau", "link": "https://stackoverflow.com/users/1838864/roy-nieterau"}, "creation_date": 1367798400, "down_vote_count": 0, "up_vote_count": 1, "post_id": 16406798, "question_id": 16405969, "timeline_type": "vote_aggregate"}], "has_more": false, "quota_max": 10000, "quota_remaining": 9498}